.gitignore
LICENSE
README.md
setup.py
tox.ini
.github/workflows/tests.yml
email_account_validity/__init__.py
email_account_validity/_base.py
email_account_validity/_store.py
email_account_validity/account_validity.py
email_account_validity/servlets.py
email_account_validity/templates/account_previously_renewed.html
email_account_validity/templates/account_renewed.html
email_account_validity/templates/invalid_token.html
email_account_validity/templates/mail-expiry.css
email_account_validity/templates/mail.css
email_account_validity/templates/notice_expiry.html
email_account_validity/templates/notice_expiry.txt
synapse_email_account_validity.egg-info/PKG-INFO
synapse_email_account_validity.egg-info/SOURCES.txt
synapse_email_account_validity.egg-info/dependency_links.txt
synapse_email_account_validity.egg-info/top_level.txt
tests/__init__.py
tests/test_account_validity.py