Metadata-Version: 2.1
Name: synapse-email-account-validity
Version: 0.3
Summary: An account validity module for Synapse using email
Home-page: https://github.com/matrix-org/synapse-email-account-validity
License: UNKNOWN
Platform: UNKNOWN
Classifier: Development Status :: 4 - Beta
Classifier: License :: OSI Approved :: Apache Software License
Classifier: Programming Language :: Python :: 3
Requires-Python: >=3.6
